{
  "graph1" : [
      {"value": 23, "date": 2007},
      {"value": 28, "date": 2012},
      {"value": 155, "date": 2013},
      {"value": 35, "date": 2006},
      {"value": 77, "date": 1990},
      {"value": 11, "date": 2036},
      {"value": 23, "date": 2016},
      {"value": 122, "date": 2044},
      {"value": 55, "date": 2002}
    ],
    "graph2": [
      {"date": 2002, "code": 1, "description": "string1"},
      {"date": 2007, "code": 2, "description": "string2"},
      {"date": 2036, "code": 3, "description": "string3"},
      {"date": 2044, "code": 4, "description": "string4"},
      {"date": 2002, "code": 5, "description": "string5"},
      {"date": 2002, "code": 6, "description": "string6"},
      {"date": 2002, "code": 7, "description": "string7"},
      {"date": 2013, "code": 8, "description": "string8"},
      {"date": 2012, "code": 9, "description": "string9"},
      {"date": 1990, "code": 10, "description": "string10"},
      {"date": 2002, "code": 11, "description": "string11"},
      {"date": 2036, "code": 12, "description": "string12"},
      {"date": 2002, "code": 13, "description": "string13"},
      {"date": 2002, "code": 14, "description": "string14"},
      {"date": 1990, "code": 15, "description": "string15"},
      {"date": 2002, "code": 16, "description": "string16"},
      {"date": 2012, "code": 17, "description": "string17"},
      {"date": 2002, "code": 18, "description": "string18"},
      {"date": 1990, "code": 19, "description": "string19"},
      {"date": 2002, "code": 20, "description": "string20"},
      {"date": 2016, "code": 21, "description": "string21"},
      {"date": 2016, "code": 22, "description": "string22"},
      {"date": 2016, "code": 23, "description": "string23"},
      {"date": 2002, "code": 24, "description": "string24"},
      {"date": 2044, "code": 25, "description": "string25"},
      {"date": 2002, "code": 26, "description": "string26"},
      {"date": 2002, "code": 27, "description": "string27"},
      {"date": 2002, "code": 28, "description": "string28"},
      {"date": 2002, "code": 29, "description": "string29"},
      {"date": 2002, "code": 30, "description": "string30"},
      {"date": 2032, "code": 31, "description": "string31"},
      {"date": 2008, "code": 32, "description": "string32"},
      {"date": 2019, "code": 33, "description": "string33"},
      {"date": 2004, "code": 34, "description": "string34"},
      {"date": 2002, "code": 35, "description": "string35"}
    ]
}